backports_abc-stubs/METADATA.toml
backports_abc-stubs/__init__.pyi
types_backports_abc-0.5.2.dist-info/METADATA
types_backports_abc-0.5.2.dist-info/WHEEL
types_backports_abc-0.5.2.dist-info/top_level.txt
types_backports_abc-0.5.2.dist-info/RECORD
