Metadata-Version: 2.1
Name: types-backports_abc
Version: 0.5.2
Summary: Typing stubs for backports_abc
Home-page: https://github.com/python/typeshed
License: Apache-2.0 license
Platform: UNKNOWN
Classifier: License :: OSI Approved :: Apache Software License
Classifier: Typing :: Stubs Only
